{
  "generatedAt": "2026-04-25T13:20:31.677Z",
  "note": "Per-rule ESLint count ratchet (#2462). Counts may only decrease. Run `npm run lint:baseline` to regenerate after a legitimate drop.",
  "counts": {
    "security/detect-object-injection": 89,
    "@typescript-eslint/no-floating-promises": 3,
    "__syntax__": 2,
    "security/detect-non-literal-fs-filename": 36,
    "no-useless-escape": 9,
    "jest/no-conditional-expect": 41,
    "no-regex-spaces": 1,
    "max-lines-per-function": 1,
    "@typescript-eslint/require-await": 2,
    "no-undef": 6,
    "@typescript-eslint/no-require-imports": 2
  }
}
